MANIFEST.in
setup.cfg
setup.py
WSME_Soap.egg-info/PKG-INFO
WSME_Soap.egg-info/SOURCES.txt
WSME_Soap.egg-info/dependency_links.txt
WSME_Soap.egg-info/entry_points.txt
WSME_Soap.egg-info/requires.txt
WSME_Soap.egg-info/top_level.txt
wsmeext/__init__.py
wsmeext/soap/__init__.py
wsmeext/soap/fault.html
wsmeext/soap/protocol.py
wsmeext/soap/soap.html
wsmeext/soap/wsdl.html
wsmeext/soap/tests/test_soap.py