Metadata-Version: 1.1
Name: WSME-Soap
Version: 0.4.1
Summary: Soap support for WSME
Home-page: UNKNOWN
Author: "Christophe de Vienne"
Author-email: "python-wsme@googlegroups.com"
License: MIT
Platform: UNKNOWN
Classifier: Development Status :: 3 - Alpha
Classifier: Operating System :: OS Independent
Classifier: Programming Language :: Python
Classifier: Programming Language :: Python :: 2.6
Classifier: Programming Language :: Python :: 2.7
Classifier: License :: OSI Approved :: MIT License
Classifier: Topic :: Internet :: WWW/HTTP :: WSGI
Classifier: Topic :: Software Development :: Libraries :: Python Modules
